LICENSE.txt
README.md
setup.py
lybluelyaioagi/__init__.py
lybluelyaioagi/lybluelyaioagi.py
lybluelyaioagi.egg-info/PKG-INFO
lybluelyaioagi.egg-info/SOURCES.txt
lybluelyaioagi.egg-info/dependency_links.txt
lybluelyaioagi.egg-info/top_level.txt