Metadata-Version: 2.1
Name: lybluelyaioagi
Version: 5.0.4
Summary: This is a test
Home-page: https://upload.pypi.org/legacy
Author: aioagi
Author-email: aioagi@aioagi.tech
Classifier: Programming Language :: Python :: 3
License-File: LICENSE.txt
